LICENSE
README.md
pyproject.toml
setup.py
korea.egg-info/PKG-INFO
korea.egg-info/SOURCES.txt
korea.egg-info/dependency_links.txt
korea.egg-info/requires.txt
korea.egg-info/top_level.txt
src/hangul/__init__.py
src/hangul/const.py
src/hangul/romanize.py
src/hangul/utils.py
src/hangul/convert/data/provisions
src/hangul/convert/data/latin/JUNGSUNG
src/hangul/convert/data/raw/CHOSUNG
src/hangul/convert/data/raw/JONGSUNG
src/hangul/convert/data/raw/JUNGSUNG
src/hangul/convert/output/latin/jungsung.json
src/hangul/convert/output/raw/chosung.json
src/hangul/convert/output/raw/jongsung.json