Metadata-Version: 2.1
Name: korea
Version: 1.1.0
Summary: Hangul Romanizer
Home-page: https://github.com/joumaico/korea
Author: Joumaico Maulas
Classifier: Development Status :: 5 - Production/Stable
Classifier: License :: OSI Approved :: MIT License
Classifier: Operating System :: OS Independent
Classifier: Programming Language :: Python :: 3.11
Classifier: Programming Language :: Python :: 3.12
Requires-Python: >=3.11
License-File: LICENSE
